{"api-b2k": {"1": {"timestamp": 1764594830.6373224, "params": {"agente_virtual_prevencao": {"value": [{"user_id": "32nbud0", "user": "olha", "password": {"salt": "544116ef3723a67e5945a7a3e50edd87", "master_key": {"iv": "430ff290f0c0254233b490de", "tag": "079e2d5d2eb87cc6ceda58103033fd5a", "data": "5b8d94d4003a97257196526922de4d22931245283de0230ebb20b70176f26690"}, "crypto_data": {"iv": "06e4fa9ff9084326dffa2fab", "tag": "747b7e6d494f6e28d22ad549fb95e2bf", "data": "07a8"}}, "status": true}, {"user_id": "k93litt", "user": "teste", "password": {"salt": "544116ef3723a67e5945a7a3e50edd87", "master_key": {"iv": "430ff290f0c0254233b490de", "tag": "079e2d5d2eb87cc6ceda58103033fd5a", "data": "5b8d94d4003a97257196526922de4d22931245283de0230ebb20b70176f26690"}, "crypto_data": {"iv": "2c07b9f0c521a01a18d3b6fd", "tag": "e833059a5b10e32e20260949aee34a00", "data": "525b10c78a5748"}}, "status": true}, {"user_id": "yaq3sjz", "user": "teste", "password": {"salt": "544116ef3723a67e5945a7a3e50edd87", "master_key": {"iv": "430ff290f0c0254233b490de", "tag": "079e2d5d2eb87cc6ceda58103033fd5a", "data": "5b8d94d4003a97257196526922de4d22931245283de0230ebb20b70176f26690"}, "crypto_data": {"iv": "204e2df5343e30054bc129b7", "tag": "b0fa36b306c9fc8c6b286773a1556941", "data": "0556cc7e36b8a253ef"}}, "status": true}], "description": "", "type": "users", "user_editable": false, "min_length": 0, "max_length": 50, "min_value": 0, "max_value": 1000000, "referenced_params": [], "created_at": "2025-11-28T19:35:05.111085", "created_by": "admin", "updated_at": "2025-12-01T12:08:42.560044", "updated_by": "admin"}, "teste": {"value": {"status": true, "user_id": "tblda8y", "user": "teste", "password": {"salt": "226828c07dfe4395cb6098ac8ececcec", "master_key": {"iv": "b26e209c2be82d81f1f8ccb0", "tag": "450e17919ce0b12c638c56247b894fdc", "data": "29aaf78722171b8734e30970a849e5c7320475a208c381edf3b0672873ec6509"}, "crypto_data": {"iv": "6c0ef0ed9cd9bae1e08d30ca", "tag": "ddb3902f7c5b150bf5d1fd684bc5ad88", "data": "0938f89dbd1eee"}}}, "description": "ok", "type": "user", "user_editable": false, "min_length": 0, "max_length": 50, "min_value": 0, "max_value": 1000000, "referenced_params": [], "created_at": "2025-12-01T13:12:12.824956", "created_by": "admin", "updated_at": "2025-12-01T13:12:12.824964", "updated_by": "admin"}}}}}